gitinfo/__init__.py
gitinfo/gitinfo.py
gitinfo/helpers.py
gitinfo/pack_reader.py
python_git_info-0.8.3.dist-info/LICENSE
python_git_info-0.8.3.dist-info/METADATA
python_git_info-0.8.3.dist-info/WHEEL
python_git_info-0.8.3.dist-info/top_level.txt
python_git_info-0.8.3.dist-info/RECORD
